MCEq/__init__.py
MCEq/charm_models.py
MCEq/config.py
MCEq/core.py
MCEq/data/README.md
MCEq/data.py
MCEq/geometry/__init__.py
MCEq/geometry/atmosphere_parameters.py
MCEq/geometry/corsikaatm/__init__.py
MCEq/geometry/corsikaatm/_libcorsikaatm.cp312-win_amd64.pyd
MCEq/geometry/corsikaatm/corsikaatm.c
MCEq/geometry/corsikaatm/corsikaatm.py
MCEq/geometry/density_profiles.py
MCEq/geometry/geometry.py
MCEq/geometry/nrlmsise00/__init__.py
MCEq/geometry/nrlmsise00/_libnrlmsise00.cp312-win_amd64.pyd
MCEq/geometry/nrlmsise00/DOCUMENTATION
MCEq/geometry/nrlmsise00/makefile
MCEq/geometry/nrlmsise00/nrlmsise-00.c
MCEq/geometry/nrlmsise00/nrlmsise-00.h
MCEq/geometry/nrlmsise00/nrlmsise-00_data.c
MCEq/geometry/nrlmsise00/nrlmsise-00_test.c
MCEq/geometry/nrlmsise00/nrlmsise00.py
MCEq/geometry/nrlmsise00_mceq.py
MCEq/misc.py
MCEq/particlemanager.py
MCEq/solvers.py
MCEq/version.py
mceq_config/__init__.py
mceq-1.3.1.dist-info/METADATA
mceq-1.3.1.dist-info/WHEEL
mceq-1.3.1.dist-info/licenses/LICENSE
mceq-1.3.1.dist-info/RECORD
