Metadata-Version: 2.2
Name: MCEq
Version: 1.3.1
Summary: Numerical cascade equation solver
Author-Email: Anatoli Fedynitch <afedynitch@gmail.com>
License: BSD 3-Clause License
Classifier: Programming Language :: Python
Classifier: Programming Language :: Python :: 3
Classifier: Topic :: Scientific/Engineering :: Physics
Classifier: Intended Audience :: Science/Research
Classifier: Development Status :: 4 - Beta
Classifier: License :: OSI Approved :: BSD License
Project-URL: Changelog, https://mceq.readthedocs.io/en/latest/en/latest/changelog.html
Project-URL: Documentation, https://mceq.readthedocs.io/en/latest
Project-URL: Homepage, https://github.com/afedynitch/MCEq
Project-URL: Issues, https://github.com/afedynitch/MCEq/issues
Requires-Dist: h5py
Requires-Dist: particletools
Requires-Dist: crflux>1.0.5
Requires-Dist: scipy
Requires-Dist: numpy
Requires-Dist: tqdm
Requires-Dist: requests
Requires-Dist: jacobi
Provides-Extra: cuda
Requires-Dist: cupy-cuda12x>=12.0.0; extra == "cuda"
